pyenttec/__init__.py
pyenttec/test.py
pyenttec-1.4.dist-info/LICENSE
pyenttec-1.4.dist-info/METADATA
pyenttec-1.4.dist-info/WHEEL
pyenttec-1.4.dist-info/top_level.txt
pyenttec-1.4.dist-info/RECORD
