Metadata-Version: 2.1
Name: pyenttec
Version: 1.4
Summary: Control an Enttec Pro DMX from python.
Home-page: UNKNOWN
Author: Chris Macklin
Author-email: chris.macklin@gmail.com
License: MIT
Platform: UNKNOWN
Requires-Dist: pyserial
